pyrimidine/.DS_Store
pyrimidine/__init__.py
pyrimidine/_stat.py
pyrimidine/base.py
pyrimidine/benchmarks/__init__.py
pyrimidine/benchmarks/approximation.py
pyrimidine/benchmarks/cluster.py
pyrimidine/benchmarks/fitting.py
pyrimidine/benchmarks/linear_model.py
pyrimidine/benchmarks/matrix.py
pyrimidine/benchmarks/neural_network.py
pyrimidine/benchmarks/optimization.py
pyrimidine/benchmarks/others.py
pyrimidine/benchmarks/special.py
pyrimidine/benchmarks/test_dataset.csv
pyrimidine/benchmarks/train_dataset.csv
pyrimidine/chromosome.py
pyrimidine/de.py
pyrimidine/deco.py
pyrimidine/ep.py
pyrimidine/errors.py
pyrimidine/es.py
pyrimidine/gene.py
pyrimidine/individual.py
pyrimidine/learn/__init__.py
pyrimidine/learn/cluster.py
pyrimidine/learn/linear_regression.py
pyrimidine/learn/neural_network.py
pyrimidine/local_search/__init__.py
pyrimidine/local_search/random_walk.py
pyrimidine/local_search/simulated_annealing.py
pyrimidine/local_search/tabu_search.py
pyrimidine/meta.py
pyrimidine/misc/__init__.py
pyrimidine/misc/aco.py
pyrimidine/misc/ba.py
pyrimidine/misc/fa.py
pyrimidine/misc/gsa.py
pyrimidine/misc/sma.py
pyrimidine/misc/ssa.py
pyrimidine/mixin.py
pyrimidine/multipopulation.py
pyrimidine/optimize.py
pyrimidine/parallel.py
pyrimidine/population.py
pyrimidine/pso.py
pyrimidine/qga.py
pyrimidine/saga.py
pyrimidine/studga.py
pyrimidine/utils.py
pyrimidine-1.7.3.dist-info/WHEEL
pyrimidine-1.7.3.dist-info/METADATA
pyrimidine-1.7.3.dist-info/RECORD
