Metadata-Version: 2.1
Name: pyrimidine
Version: 1.7.3
Summary: A competitive framework tailored for GA, crafted with an emphasis on OOP and Algebra-Inspired Programming.
Home-page: https://github.com/Freakwill/pyrimidine
License: MIT
Keywords: Genetic Algorithm,Artificial Intelligence,Intelligent Optimization
Author: William Song
Author-email: 30965609+Freakwill@users.noreply.github.com
Requires-Python: >=3.9,<4.0
Classifier: Environment :: MacOS X
Classifier: Intended Audience :: Science/Research
Classifier: License :: OSI Approved :: MIT License
Classifier: Operating System :: OS Independent
Classifier: Programming Language :: Python :: 3
Classifier: Programming Language :: Python :: 3.10
Classifier: Programming Language :: Python :: 3.9
Classifier: Topic :: Scientific/Engineering :: Artificial Intelligence
Classifier: Topic :: Software Development :: Libraries :: Python Modules
Requires-Dist: matplotlib (>=3.9.0,<4.0.0)
Requires-Dist: numpy (>=2.0.0,<3.0.0)
Requires-Dist: pandas (>=2.1.0,<3.0.0)
Requires-Dist: scikit-learn (>=1.4.0,<2.0.0)
Requires-Dist: scipy (>=1.12.0,<2.0.0)
Requires-Dist: toolz (>=0.12.0,<0.13.0)
Project-URL: Repository, https://github.com/Freakwill/pyrimidine
